odoo/addons/account_payment_return_import_sepa_pain/README.rst
odoo/addons/account_payment_return_import_sepa_pain/__init__.py
odoo/addons/account_payment_return_import_sepa_pain/__manifest__.py
odoo/addons/account_payment_return_import_sepa_pain/data/unpaid_reason_codes.xml
odoo/addons/account_payment_return_import_sepa_pain/i18n/de.po
odoo/addons/account_payment_return_import_sepa_pain/i18n/es.po
odoo/addons/account_payment_return_import_sepa_pain/i18n/sl.po
odoo/addons/account_payment_return_import_sepa_pain/models/__init__.py
odoo/addons/account_payment_return_import_sepa_pain/models/payment_return.py
odoo/addons/account_payment_return_import_sepa_pain/static/description/icon.png
odoo/addons/account_payment_return_import_sepa_pain/static/description/icon.svg
odoo/addons/account_payment_return_import_sepa_pain/test_files/test-sepa-unpaid.xml
odoo/addons/account_payment_return_import_sepa_pain/test_files/test-sepa-unpaid.zip
odoo/addons/account_payment_return_import_sepa_pain/tests/__init__.py
odoo/addons/account_payment_return_import_sepa_pain/tests/test_import_sepa_pain.py
odoo/addons/account_payment_return_import_sepa_pain/wizard/__init__.py
odoo/addons/account_payment_return_import_sepa_pain/wizard/pain_parser.py
odoo/addons/account_payment_return_import_sepa_pain/wizard/payment_return_import.py
odoo11_addon_account_payment_return_import_sepa_pain-11.0.1.0.0.dist-info/DESCRIPTION.rst
odoo11_addon_account_payment_return_import_sepa_pain-11.0.1.0.0.dist-info/METADATA
odoo11_addon_account_payment_return_import_sepa_pain-11.0.1.0.0.dist-info/RECORD
odoo11_addon_account_payment_return_import_sepa_pain-11.0.1.0.0.dist-info/WHEEL
odoo11_addon_account_payment_return_import_sepa_pain-11.0.1.0.0.dist-info/metadata.json
odoo11_addon_account_payment_return_import_sepa_pain-11.0.1.0.0.dist-info/top_level.txt
